USR_flow/RTL_design_Verification/behav_design/UAR_behav_8bit.v
module UAR_behav_8bit (
    input wire [7:0] d_in,    // 8-bit parallel data input
    input wire clk,           // Clock signal
    input wire [1:0] select,  // Control signals S1, S0
    output reg [7:0] q        // 8-bit register output
);

always @(posedge clk) begin
    case (select)
        2'b00: q <= q;                       // Hold: Keep the current value
        2'b01: q <= {1'b0, q[7:1]};          // Shift Right: Insert 0 from the left
        2'b10: q <= {q[6:0], 1'b0};          // Shift Left: Insert 0 from the right
        2'b11: q <= d_in;                    // Parallel Load: Load new data
        default: q <= q;                     // Default to hold
    endcase
end

initial begin
    $dumpfile("dump_1 .vcd");  // Generate the VCD file
    $dumpvars(0, UAR_behav_8bit);  // Dump all variables in the top-level module
end

endmodule

USR_flow/RTL_design_Verification/behav_design/dump_2.vcd
$date
	Sat Oct  5 21:29:44 2024
$end
$version
	Icarus Verilog
$end
$timescale
	1ps
$end
$scope module UAR_behav_8bit $end
$var wire 1 ! clk $end
$var wire 8 " d_in [7:0] $end
$var wire 2 # select [1:0] $end
$var reg 8 $ q [7:0] $end
$upscope $end
$enddefinitions $end
$comment Show the parameter values. $end
$dumpall
$end
#0
$dumpvars
bx $
b0 #
b0 "
1!
$end
#5000
0!
#10000
b11 #
b10101010 "
1!
#15000
0!
#20000
b10 #
b10101010 $
1!
#25000
0!
#30000
b1 #
b1010100 $
1!
#35000
0!
#40000
b0 #
b101010 $
1!
#45000
0!
#50000
b11 #
b11001010 "
1!
#55000
0!
#60000
b10 #
b11001010 $
1!
#65000
0!
#70000
b1 #
b10010100 $
1!
#75000
0!
#80000
b0 #
b1001010 $
1!
