USR_flow/RTL_design_Verification/behav_design/UAR_behav_8bit.v
module UAR_behav_8bit (
    input wire [7:0] d_in,    // 8-bit parallel data input
    input wire clk,           // Clock signal
    input wire [1:0] select,  // Control signals S1, S0
    output reg [7:0] q        // 8-bit register output
);

always @(posedge clk) begin
    case (select)
        2'b00: q <= q;                       // Hold: Keep the current value
        2'b01: q <= {1'b0, q[7:1]};          // Shift Right: Insert 0 from the left
        2'b10: q <= {q[6:0], 1'b0};          // Shift Left: Insert 0 from the right
        2'b11: q <= d_in;                    // Parallel Load: Load new data
        default: q <= q;                     // Default to hold
    endcase
end

initial begin
    $dumpfile("dump_1 .vcd");  // Generate the VCD file
    $dumpvars(0, UAR_behav_8bit);  // Dump all variables in the top-level module
end

endmodule

USR_flow/RTL_design_Verification/behav_design/tb_UAR.sv
module tb_UAR;

// Inputs to DUT
reg [7:0] d_in;
reg clk;
reg [1:0] select;

// Output from DUT
wire [7:0] q;

// Instantiate the DUT (Design Under Test)
UAR_behav_8bit dut (
    .d_in(d_in),
    .clk(clk),
    .select(select),
    .q(q)
);

// Clock generation
initial begin
    clk = 0;
    forever #5 clk = ~clk;  // Clock period = 10 time units
end

// Test procedure
initial begin
    // Apply reset-like behavior
    d_in = 4'b0000;
    select = 2'b00;  // Hold
    #10;

    // Parallel load 4'b1010 into the register
    d_in = 4'b1010;
    select = 2'b11;  // Parallel load
    #10;
    
    // Test shift left
    select = 2'b10;
    #10;

    // Test shift right
    select = 2'b01;
    #10;

    // Hold the current value
    select = 2'b00;
    #10;
    
    // Parallel load another value 4'b1100
    d_in = 4'b1100;
    select = 2'b11;
    #10;

    // Test additional shifts and hold operations
    select = 2'b10;  // Shift left
    #10;
    select = 2'b00;  // Hold
    #10;
    select = 2'b01;  // Shift right
    #10;

    // Finish simulation
    $finish;
end

// Monitor the changes
initial begin
    $monitor("At time %t: d_in = %b, select = %b, q = %b", $time, d_in, select, q);
end

endmodule

USR_flow/RTL_design_Verification/behav_design/dump_1.vcd
$date
	Sat Oct  5 21:50:23 2024
$end
$version
	Icarus Verilog
$end
$timescale
	1s
$end
$scope module tb_UAR $end
$scope module dut $end
$var wire 1 ! clk $end
$var wire 8 " d_in [7:0] $end
$var wire 2 # select [1:0] $end
$var reg 8 $ q [7:0] $end
$upscope $end
$upscope $end
$enddefinitions $end
$comment Show the parameter values. $end
$dumpall
$end
#0
$dumpvars
bx $
b0 #
b0 "
0!
$end
#5
1!
#10
0!
b11 #
b1010 "
#15
b1010 $
1!
#20
0!
b10 #
#25
b10100 $
1!
#30
0!
b1 #
#35
b1010 $
1!
#40
0!
b0 #
#45
1!
#50
0!
b11 #
b1100 "
#55
b1100 $
1!
#60
0!
b10 #
#65
b11000 $
1!
#70
0!
b0 #
#75
1!
#80
0!
b1 #
#85
b1100 $
1!
